ttastromech/__init__.py
ttastromech/bin/astromechspeak.py
ttastromech/sounds/a.wav
ttastromech/sounds/b.wav
ttastromech/sounds/c.wav
ttastromech/sounds/c1.wav
ttastromech/sounds/d.wav
ttastromech/sounds/e.wav
ttastromech/sounds/f.wav
ttastromech/sounds/g.wav
ttastromech/sounds/g1.wav
ttastromech/sounds/h.wav
ttastromech/sounds/i.wav
ttastromech/sounds/j.wav
ttastromech/sounds/k.wav
ttastromech/sounds/l.wav
ttastromech/sounds/m.wav
ttastromech/sounds/n.wav
ttastromech/sounds/o.wav
ttastromech/sounds/o1.wav
ttastromech/sounds/p.wav
ttastromech/sounds/q.wav
ttastromech/sounds/r.wav
ttastromech/sounds/s.wav
ttastromech/sounds/s1.wav
ttastromech/sounds/t.wav
ttastromech/sounds/u.wav
ttastromech/sounds/u1.wav
ttastromech/sounds/v.wav
ttastromech/sounds/w.wav
ttastromech/sounds/x.wav
ttastromech/sounds/y.wav
ttastromech/sounds/z.wav
ttastromech/ttastromech.py
ttastromech/ttastromech_pyaudio.py
ttastromech-0.6.1.dist-info/LICENSE
ttastromech-0.6.1.dist-info/METADATA
ttastromech-0.6.1.dist-info/WHEEL
ttastromech-0.6.1.dist-info/entry_points.txt
ttastromech-0.6.1.dist-info/RECORD
