Metadata-Version: 2.1
Name: ttastromech
Version: 0.6.1
Summary: python library transform text strings into Astromech (like R2D2) sounds
Home-page: https://pypi.org/project/ttastromech/
License: MIT
Keywords: r2d2,tts,star wars,droid,astromech
Author: walchko
Author-email: walchko@users.noreply.github.com
Requires-Python: >=3.8
Classifier: Development Status :: 4 - Beta
Classifier: Intended Audience :: Developers
Classifier: License :: OSI Approved :: MIT License
Classifier: Operating System :: OS Independent
Classifier: Programming Language :: Python :: 3
Classifier: Programming Language :: Python :: 3.8
Classifier: Programming Language :: Python :: 3.9
Classifier: Programming Language :: Python :: 3.10
Classifier: Programming Language :: Python :: 3.11
Classifier: Programming Language :: Python :: 3.12
Classifier: Programming Language :: Python :: 3.13
Classifier: Topic :: Software Development :: Libraries
Classifier: Topic :: Software Development :: Libraries :: Application Frameworks
Classifier: Topic :: Software Development :: Libraries :: Python Modules
Project-URL: Repository, http://github.com/MomsFriendlyRobotCompany/ttastromech
